wj_credentials/__init__.py
wj_credentials/configuration.py
wj_credentials-0.1.1.dist-info/LICENSE.md
wj_credentials-0.1.1.dist-info/WHEEL
wj_credentials-0.1.1.dist-info/METADATA
wj_credentials-0.1.1.dist-info/RECORD
