Metadata-Version: 2.1
Name: wj-credentials
Version: 0.1.1
Summary: Whale&Jaguar Libary - Credentials
License: GNU3
Author: Sebastian Franco
Author-email: jsfranco@whaleandjaguar.co
Requires-Python: >3.6.1,<4.0
Classifier: License :: Other/Proprietary License
Classifier: Programming Language :: Python :: 3
Classifier: Programming Language :: Python :: 3.7
Classifier: Programming Language :: Python :: 3.8
Classifier: Programming Language :: Python :: 3.9
Requires-Dist: boto3 (==1.14.52)
